MANIFEST.in
setup.py
expanalysis/__init__.py
expanalysis/api.py
expanalysis/maths.py
expanalysis/results.py
expanalysis/stats.py
expanalysis/testing.py
expanalysis/utils.py
expanalysis.egg-info/PKG-INFO
expanalysis.egg-info/SOURCES.txt
expanalysis.egg-info/dependency_links.txt
expanalysis.egg-info/not-zip-safe
expanalysis.egg-info/pbr.json
expanalysis.egg-info/requires.txt
expanalysis.egg-info/top_level.txt
expanalysis/experiments/stroop/stroop_condition_vs_reactiontime.ipynb
expanalysis/experiments/stroop/stroop_condition_vs_reactiontime.py
expanalysis/experiments/stroop/stroop_results.csv
expanalysis/tests/run_tests.sh
expanalysis/tests/test_api.py
expanalysis/tests/test_api.pyc
expanalysis/tests/data/results/results.json
expanalysis/tests/data/results/results_old.json